lisql.py
lisql-2.1.86.dist-info/LICENSE
lisql-2.1.86.dist-info/METADATA
lisql-2.1.86.dist-info/WHEEL
lisql-2.1.86.dist-info/top_level.txt
lisql-2.1.86.dist-info/RECORD
