Metadata-Version: 2.1
Name: lisql
Version: 2.1.86
Summary: Provides simple funtions to interact with MySQL databases and tables.
Home-page: https://github.com/li812/lisql
Author: Ali Ahammad
Author-email: aliahammad0812@outlook.com
Project-URL: Bug Tracker, https://github.com/li812/lisql/issues
Classifier: License :: OSI Approved :: MIT License
Classifier: Programming Language :: Python :: 3
Classifier: Programming Language :: Python :: 3.6
Classifier: Programming Language :: Python :: 3.7
Classifier: Programming Language :: Python :: 3.8
Classifier: Programming Language :: Python :: 3.9
Classifier: Programming Language :: Python :: 3.10
Classifier: Programming Language :: Python :: 3.11
Requires-Python: >=3.6
License-File: LICENSE
